wallpaper_app/__init__.py
wallpaper_app/image_handler.py
wallpaper_app/statusbar_app.py
wallpaper_app-0.0.1.dist-info/entry_points.txt
wallpaper_app-0.0.1.dist-info/WHEEL
wallpaper_app-0.0.1.dist-info/METADATA
wallpaper_app-0.0.1.dist-info/RECORD
